dhosting/__init__.py
dhosting/adapter.py
dhosting/base_email.py
dhosting/connection.py
dhosting/exceptions.py
dhosting/utils.py
dhosting_api/__init__.py
dhosting_api/adapter.py
dhosting_api/base_email.py
dhosting_api/connection.py
dhosting_api/exceptions.py
dhosting_api/utils.py
dhosting_api-1.0.dist-info/METADATA
dhosting_api-1.0.dist-info/WHEEL
dhosting_api-1.0.dist-info/top_level.txt
dhosting_api-1.0.dist-info/RECORD
