Metadata-Version: 2.1
Name: dhosting-api
Version: 1.0
Summary: Package to connect with dhosting_api
Author: Maks Galbierczyk
Author-email: maksymilian.galbierczyk@apz.pl
License: MIT
Requires-Dist: Django
Requires-Dist: requests
